events_calendar/__init__.py
django_events_calendar-2023.8.3.dist-info/METADATA
django_events_calendar-2023.8.3.dist-info/WHEEL
django_events_calendar-2023.8.3.dist-info/licenses/LICENSE
django_events_calendar-2023.8.3.dist-info/RECORD
