Metadata-Version: 2.1
Name: django-events-calendar
Version: 2023.8.3
Summary: Easily create and manage an events calendar on your Django site
Author-email: Atem18 <contact@atemlire.io>
License: MIT License
License-File: LICENSE
Keywords: calendar,events
Classifier: License :: OSI Approved :: MIT License
Classifier: Programming Language :: Python :: 3 :: Only
Classifier: Programming Language :: Python :: 3.8
Classifier: Programming Language :: Python :: 3.9
Classifier: Programming Language :: Python :: 3.10
Classifier: Programming Language :: Python :: 3.11
Requires-Dist: django>=3.2
Provides-Extra: build
Requires-Dist: hatch==1.7.0; extra == 'build'
Provides-Extra: dev
Requires-Dist: mypy==1.4.1; extra == 'dev'
Requires-Dist: pre-commit<4.0.0,>=2.17.0; extra == 'dev'
Requires-Dist: ruff==0.0.280; extra == 'dev'
Provides-Extra: doc
Requires-Dist: mkdocs-material==9.1.21; extra == 'doc'
Requires-Dist: mkdocs==1.5.1; extra == 'doc'
Requires-Dist: mkdocstrings==0.22.0; extra == 'doc'
Provides-Extra: test
Requires-Dist: pytest==7.4.0; extra == 'test'
Requires-Dist: tox==4.6.4; extra == 'test'
